[
  {
    "id": 1,
    "nome": "Leanne Graham",
    "email": "Sincere@april.biz"
  },
  {
    "id": 2,
    "nome": "Ervin Howell",
    "email": "Shanna@melissa.tv"
  },
  {
    "id": 3,
    "nome": "Clementine Bauch",
    "email": "Nathan@yesenia.net"
  },
  {
    "id": 4,
    "nome": "Patricia Lebsack",
    "email": "Julianne.OConner@kory.org"
  },
  {
    "id": 5,
    "nome": "Chelsey Dietrich",
    "email": "Lucio_Hettinger@annie.ca"
  },
  {
    "id": 6,
    "nome": "Mrs. Dennis Schulist",
    "email": "Karley_Dach@jasper.info"
  },
  {
    "id": 7,
    "nome": "Kurtis Weissnat",
    "email": "Telly.Hoeger@billy.biz"
  },
  {
    "id": 8,
    "nome": "Nicholas Runolfsdottir V",
    "email": "Sherwood@rosamond.me"
  },
  {
    "id": 9,
    "nome": "Glenna Reichert",
    "email": "Chaim_McDermott@dana.io"
  },
  {
    "id": 10,
    "nome": "Clementina DuBuque",
    "email": "Rey.Padberg@karina.biz"
  }
]